presidio_evaluator/__init__.py
presidio_evaluator/data_generator/README.md
presidio_evaluator/data_generator/__init__.py
presidio_evaluator/data_generator/faker_extensions/__init__.py
presidio_evaluator/data_generator/faker_extensions/data_objects.py
presidio_evaluator/data_generator/faker_extensions/datasets.py
presidio_evaluator/data_generator/faker_extensions/providers.py
presidio_evaluator/data_generator/faker_extensions/sentences.py
presidio_evaluator/data_generator/faker_extensions/span_generator.py
presidio_evaluator/data_generator/presidio_data_generator.py
presidio_evaluator/data_generator/presidio_pseudonymize.py
presidio_evaluator/data_generator/presidio_sentence_faker.py
presidio_evaluator/data_generator/raw_data/FakeNameGenerator.com_3000.csv
presidio_evaluator/data_generator/raw_data/companies_and_organizations.csv
presidio_evaluator/data_generator/raw_data/nationalities.csv
presidio_evaluator/data_generator/raw_data/religions.csv
presidio_evaluator/data_generator/raw_data/templates.txt
presidio_evaluator/data_generator/raw_data/us_driver_license_format.yaml
presidio_evaluator/data_generator/raw_data/us_driver_licenses.csv
presidio_evaluator/data_objects.py
presidio_evaluator/dataset_formatters/__init__.py
presidio_evaluator/dataset_formatters/conll_formatter.py
presidio_evaluator/dataset_formatters/dataset_formatter.py
presidio_evaluator/dataset_formatters/i2b2_formatter.py
presidio_evaluator/evaluation/__init__.py
presidio_evaluator/evaluation/base_evaluator.py
presidio_evaluator/evaluation/evaluation_result.py
presidio_evaluator/evaluation/model_error.py
presidio_evaluator/evaluation/plotter.py
presidio_evaluator/evaluation/scorers.py
presidio_evaluator/evaluation/skipwords.py
presidio_evaluator/evaluation/span_evaluator.py
presidio_evaluator/evaluation/token_evaluator.py
presidio_evaluator/experiment_tracking/__init__.py
presidio_evaluator/experiment_tracking/experiment_tracker.py
presidio_evaluator/experiment_tracking/local_tracker.py
presidio_evaluator-0.2.5.dist-info/LICENSE
presidio_evaluator-0.2.5.dist-info/METADATA
presidio_evaluator-0.2.5.dist-info/NOTICE
presidio_evaluator-0.2.5.dist-info/WHEEL
presidio_evaluator-0.2.5.dist-info/RECORD
