Metadata-Version: 2.3
Name: presidio_evaluator
Version: 0.2.5
Summary: 
License: MIT
Author: Microsoft
Requires-Python: >=3.10,<4.0
Classifier: License :: OSI Approved :: MIT License
Classifier: Programming Language :: Python :: 3
Classifier: Programming Language :: Python :: 3.10
Classifier: Programming Language :: Python :: 3.11
Classifier: Programming Language :: Python :: 3.12
Classifier: Programming Language :: Python :: 3.13
Requires-Dist: faker
Requires-Dist: numpy (>=2.0.0,<3.0.0)
Requires-Dist: pandas (>=2.1.4,<3.0.0)
Requires-Dist: plotly (>=5.24.0,<6.0.0)
Requires-Dist: presidio-analyzer (>=2.2.351,<3.0.0)
Requires-Dist: presidio-anonymizer (>=2.2.351,<3.0.0)
Requires-Dist: python-dotenv (>=1.0.0,<2.0.0)
Requires-Dist: requests (>=2.25,<3.0)
Requires-Dist: scikit-learn (>=1.3.2,<2.0.0)
Requires-Dist: spacy (<3.8.4) ; python_version < "3.10"
Requires-Dist: tqdm (>=4.60.0,<5.0.0)
Requires-Dist: xmltodict (>=0.12.0,<0.13.0)
